onegov.gazette-1.25.0-py3.6-nspkg.pth
onegov/gazette/.gitignore
onegov/gazette/__init__.py
onegov/gazette/app.py
onegov/gazette/cli.py
onegov/gazette/fields.py
onegov/gazette/layout.py
onegov/gazette/path.py
onegov/gazette/pdf.py
onegov/gazette/translations.py
onegov/gazette/upgrade.py
onegov/gazette/validators.py
onegov/gazette/assets/css/jquery.datetimepicker.css
onegov/gazette/assets/js/common.js
onegov/gazette/assets/js/datetimepicker.js
onegov/gazette/assets/js/dropzone.js
onegov/gazette/assets/js/foundation.js
onegov/gazette/assets/js/jquery.datetimepicker.full.js
onegov/gazette/assets/js/jquery.js
onegov/gazette/assets/js/modernizr.js
onegov/gazette/assets/js/sortable.js
onegov/gazette/assets/js/sortable_custom.js
onegov/gazette/assets/js/stacktable.js
onegov/gazette/assets/js/underscore.js
onegov/gazette/collections/__init__.py
onegov/gazette/collections/categories.py
onegov/gazette/collections/issues.py
onegov/gazette/collections/notices.py
onegov/gazette/collections/organizations.py
onegov/gazette/forms/__init__.py
onegov/gazette/forms/category.py
onegov/gazette/forms/common.py
onegov/gazette/forms/issue.py
onegov/gazette/forms/notice.py
onegov/gazette/forms/organization.py
onegov/gazette/forms/user.py
onegov/gazette/locale/de_CH/LC_MESSAGES/onegov.gazette.po
onegov/gazette/models/__init__.py
onegov/gazette/models/category.py
onegov/gazette/models/issue.py
onegov/gazette/models/notice.py
onegov/gazette/models/organization.py
onegov/gazette/models/principal.py
onegov/gazette/static/font-awesome/css/font-awesome.css
onegov/gazette/static/font-awesome/css/font-awesome.min.css
onegov/gazette/static/font-awesome/fonts/FontAwesome.otf
onegov/gazette/static/font-awesome/fonts/fontawesome-webfont.eot
onegov/gazette/static/font-awesome/fonts/fontawesome-webfont.svg
onegov/gazette/static/font-awesome/fonts/fontawesome-webfont.ttf
onegov/gazette/static/font-awesome/fonts/fontawesome-webfont.woff
onegov/gazette/static/font-awesome/fonts/fontawesome-webfont.woff2
onegov.gazette-1.25.0.dist-info/METADATA
onegov.gazette-1.25.0.dist-info/WHEEL
onegov.gazette-1.25.0.dist-info/entry_points.txt
onegov.gazette-1.25.0.dist-info/namespace_packages.txt
onegov.gazette-1.25.0.dist-info/top_level.txt
onegov.gazette-1.25.0.dist-info/RECORD
