Metadata-Version: 2.1
Name: onegov.gazette
Version: 1.25.0
Summary: OneGov official notices website.
Home-page: http://github.com/onegov/onegov.gazette
Author: Seantis GmbH
Author-email: info@seantis.ch
License: GPLv2
Platform: any
Classifier: Intended Audience :: Developers
Classifier: Programming Language :: Python :: 3 :: Only
Classifier: Programming Language :: Python :: 3.6
Classifier: Programming Language :: Python :: 3.7
Classifier: Topic :: Software Development :: Libraries :: Python Modules
Classifier: License :: OSI Approved :: GNU General Public License v2 (GPLv2)
Requires-Python: >=3.6
Requires-Dist: babel
Requires-Dist: cached-property
Requires-Dist: cssmin
Requires-Dist: onegov.chat
Requires-Dist: onegov.core (>=0.79.1)
Requires-Dist: onegov.file
Requires-Dist: onegov.form (>=0.43.0)
Requires-Dist: onegov.foundation
Requires-Dist: onegov.notice (>=0.11.1)
Requires-Dist: onegov.pdf (>=0.5.0)
Requires-Dist: onegov.quill (>=0.5.0)
Requires-Dist: onegov.shared
Requires-Dist: onegov.user (>=0.18.0)
Requires-Dist: python-dateutil
Requires-Dist: pyyaml
Requires-Dist: rjsmin
Requires-Dist: sedate
Requires-Dist: xlrd
Requires-Dist: xlsxwriter
Provides-Extra: test
Requires-Dist: coverage ; extra == 'test'
Requires-Dist: freezegun ; extra == 'test'
Requires-Dist: mock ; extra == 'test'
Requires-Dist: onegov-testing ; extra == 'test'
Requires-Dist: pyquery ; extra == 'test'
Requires-Dist: pytest-localserver ; extra == 'test'
Requires-Dist: pytest ; extra == 'test'
Requires-Dist: PyPDF2 ; extra == 'test'
Requires-Dist: webtest ; extra == 'test'
